django_kanboard/__about__.py
django_kanboard/__init__.py
django_kanboard/admin/__init__.py
django_kanboard/admin/forms.py
django_kanboard/apps.py
django_kanboard/kanboard_wrapper.py
django_kanboard/locale/fr/LC_MESSAGES/django.mo
django_kanboard/locale/fr/LC_MESSAGES/django.po
django_kanboard/management/__init__.py
django_kanboard/management/commands/__init__.py
django_kanboard/management/commands/sync_project_templates.py
django_kanboard/migrations/0001_initial.py
django_kanboard/migrations/__init__.py
django_kanboard/models/__init__.py
django_kanboard/models/config.py
django_kanboard/models/helpers.py
django_kanboard/views.py
django_kanboard-0.6.0.dist-info/WHEEL
django_kanboard-0.6.0.dist-info/METADATA
django_kanboard-0.6.0.dist-info/RECORD
