Metadata-Version: 2.3
Name: django-kanboard
Version: 0.6.0
Summary: Project management with help of kanboard.
Keywords: Kanboard,Django,Project management,Scheduling
Author: François GUÉRIN
Author-email: François GUÉRIN <fguerin@ville-tourcoing.fr>
License: MIT License
Classifier: Development Status :: 4 - Beta
Classifier: Environment :: Web Environment
Classifier: Framework :: Django
Classifier: Framework :: Django :: 3.2
Classifier: Intended Audience :: Developers
Classifier: License :: OSI Approved :: MIT License
Classifier: Operating System :: OS Independent
Classifier: Programming Language :: Python :: 3
Classifier: Programming Language :: Python :: 3.9
Classifier: Programming Language :: Python :: 3.10
Classifier: Programming Language :: Python :: 3.11
Classifier: Topic :: Office/Business :: Scheduling
Requires-Dist: kanboard>=1.1.2
Requires-Dist: django>=3.2,<6.0
Requires-Dist: django-solo>=2.3.0
Requires-Dist: django-reversion>=3.0.9
Requires-Dist: django-colorfield>=0.4.1
Requires-Dist: django-currentuser>=0.5.3
Requires-Dist: requests>=2.25.0
Requires-Dist: django-ckeditor-5==0.2.13
Maintainer: François GUÉRIN
Maintainer-email: François GUÉRIN <fguerin@ville-tourcoing.fr>
Requires-Python: >=3.11
Project-URL: Homepage, https://gitlab.ville.tg/fguerin/django-kanboard/
